prompt_as_method/__init__.py
prompt_as_method/__main__.py
prompt_as_method/data.py
prompt_as_method/llm.py
prompt_as_method/method.py
prompt_as_method/prompt.py
prompt_as_method/prompt_template.py
prompt_as_method/task.py
prompt_as_method-0.4.0.dist-info/LICENSE
prompt_as_method-0.4.0.dist-info/METADATA
prompt_as_method-0.4.0.dist-info/WHEEL
prompt_as_method-0.4.0.dist-info/RECORD
