Metadata-Version: 2.3
Name: prompt-as-method
Version: 0.4.0
Summary: Run prompts from files
License: MIT License
Keywords: ai,artificial intelligence,classification,generative model,large language model,llm,prompt
Author: Johannes Kiesel
Author-email: Johannes.Kiesel@gesis.org
Maintainer: Johannes Kiesel
Maintainer-email: Johannes.Kiesel@gesis.org
Requires-Python: >=3.10,<4.0
Classifier: License :: Other/Proprietary License
Classifier: Programming Language :: Python :: 3
Classifier: Programming Language :: Python :: 3.10
Classifier: Programming Language :: Python :: 3.11
Classifier: Programming Language :: Python :: 3.12
Classifier: Programming Language :: Python :: 3.13
Requires-Dist: chevron (>=0.14.0)
Requires-Dist: json-repair (>=0.46.0,<0.47.0)
Requires-Dist: jsonref (>=1.1.0,<2.0.0)
Requires-Dist: jsonschema (>=4.23.0)
Requires-Dist: jsonschema-fill-default (>=0.1.3.20250131,<0.2.0.0)
Requires-Dist: pydantic (>=2.10.6)
Requires-Dist: requests (>=2.32.3)
Project-URL: Issues, https://github.com/GESIS-Methods-Hub/prompt-as-method/issues
Project-URL: Source, https://github.com/GESIS-Methods-Hub/prompt-as-method
